PyInfoComp/PyInfoComp.py
PyInfoComp/__init__.py
PyInfoComp-1.1.0.dist-info/LICENSE.txt
PyInfoComp-1.1.0.dist-info/METADATA
PyInfoComp-1.1.0.dist-info/WHEEL
PyInfoComp-1.1.0.dist-info/top_level.txt
PyInfoComp-1.1.0.dist-info/RECORD
