Metadata-Version: 2.1
Name: PyInfoComp
Version: 1.1.0
Summary: Infopy is a Python module that provides a collection of methods to retrieve essential system information. With this module, you can easily get details about your system's hardware and software, such as the CPU, GPU, RAM, battery status, network information, uptime, and more. It also supports retrieving public IP addresses, Wi-Fi profiles, clipboard contents, and system OS information.
Home-page: https://github.com/froxxy1011/PyInfo
Author: Jamil Formuly
Author-email: Jamilformuly12345@gmail.com
Classifier: Programming Language :: Python :: 3
Classifier: License :: OSI Approved :: MIT License
Classifier: Operating System :: OS Independent
Requires-Python: >=3.6
License-File: LICENSE.txt
Requires-Dist: requests
Requires-Dist: psutil
Requires-Dist: pyperclip
Requires-Dist: wmi
